melange_algorithm/__init__.py
melange_algorithm/active_learning.py
melange_algorithm/main.py
melange_algorithm/test.py
melange_algorithm/transfer_learning.py
melange_algorithm-0.2.dist-info/DESCRIPTION.rst
melange_algorithm-0.2.dist-info/METADATA
melange_algorithm-0.2.dist-info/RECORD
melange_algorithm-0.2.dist-info/WHEEL
melange_algorithm-0.2.dist-info/metadata.json
melange_algorithm-0.2.dist-info/top_level.txt
