Metadata-Version: 2.0
Name: melange-algorithm
Version: 0.2
Summary: Melange Algorithms
Home-page: UNKNOWN
Author: ck
Author-email: UNKNOWN
License: UNKNOWN
Platform: UNKNOWN
